orango.py
orango-0.1.0.dist-info/METADATA
orango-0.1.0.dist-info/WHEEL
orango-0.1.0.dist-info/RECORD
