Metadata-Version: 2.1
Name: orango
Version: 0.1.0
Summary: Secure sandboxed cloud and edge environments made for AI agents and AI apps
Author: Orango AI
Author-email: hello@orango.ai
Requires-Python: >=3.10,<4.0
Classifier: Programming Language :: Python :: 3
Classifier: Programming Language :: Python :: 3.10
Classifier: Programming Language :: Python :: 3.11
Classifier: Programming Language :: Python :: 3.12
Requires-Dist: requests (>=2.32.3,<3.0.0)
